Metadata-Version: 1.0
Name: cep
Version: 0.1
Summary: Pesquisa de CEPs via site dos Correios
Home-page: https://github.com/jbochi/cep
Author: Juarez Bochi
Author-email: jbochi@gmail.com
License: MIT
Platform: any
Classifier: Development Status :: 4 - Beta
Classifier: Operating System :: OS Independent
Classifier: Environment :: No Input/Output (Daemon)
Classifier: Intended Audience :: Developers
Classifier: License :: OSI Approved :: MIT License
Classifier: Natural Language :: Portuguese (Brazilian)
Classifier: Programming Language :: Python :: 2.5
Classifier: Programming Language :: Python :: 2.6
Classifier: Programming Language :: Python :: 2.7
Classifier: Topic :: Internet
